controller/BuildPlanDetail.py
controller/CommitToPlan.py
controller/DB.py
controller/GetMethod.py
controller/__init__.py
BuildPlanDetail-2.2.1.dist-info/METADATA
BuildPlanDetail-2.2.1.dist-info/WHEEL
BuildPlanDetail-2.2.1.dist-info/top_level.txt
BuildPlanDetail-2.2.1.dist-info/RECORD
