Metadata-Version: 2.1
Name: BuildPlanDetail
Version: 2.2.1
Summary: 获取代码改动的文件和方法
Home-page: https://github.com/vfrtgb158/email
Author: houyan
Author-email: houyan@qiyi.com
License: MIT
Platform: UNKNOWN
Requires: requests
Requires: pygerrit2
Requires: PyMySQL
Requires: multiprocess
Requires: threadpool
